<?xml version="1.0" encoding="utf-8"?>
<Map>
  <Settings MapWidth="30" MapHeight="80" TilesetWidth="16" TilesetHeight="16" TileWidth="16" TileHeight="16" />

	<!-- BEGIN SCREEN 1 -->
  <Tile Type="1" posX="464" posY="0" />
  <Tile Type="2" posX="464" posY="16" />
  <Tile Type="1" posX="464" posY="32" />
  <Tile Type="2" posX="464" posY="48" />
  <Tile Type="1" posX="464" posY="64" />
  <Tile Type="2" posX="464" posY="80" />
  <Tile Type="1" posX="464" posY="96" />
  <Tile Type="2" posX="464" posY="112" />
  <Tile Type="1" posX="464" posY="128" />
  <Tile Type="2" posX="464" posY="144" />
  <Tile Type="1" posX="464" posY="160" />
  <Tile Type="2" posX="464" posY="176" />
  <Tile Type="1" posX="464" posY="192" />
  <Tile Type="2" posX="464" posY="208" />
  <Tile Type="1" posX="464" posY="224" />
  <Tile Type="2" posX="464" posY="240" />
  <Tile Type="1" posX="464" posY="256" />
  <Tile Type="2" posX="464" posY="272" />
  <Tile Type="1" posX="464" posY="288" />
  <Tile Type="2" posX="464" posY="304" />
  <Tile Type="1" posX="464" posY="320" />
  <Tile Type="2" posX="464" posY="336" />
  <Tile Type="1" posX="464" posY="352" />
  <Tile Type="2" posX="464" posY="368" />
  <Tile Type="32" posX="448" posY="384" />
  <Tile Type="51" posX="464" posY="384" />
  <Tile Type="2" posX="448" posY="400" />
  <Tile Type="85" posX="464" posY="400" />
  <Tile Type="32" posX="432" posY="416" />
  <Tile Type="51" posX="448" posY="416" />
  <Tile Type="85" posX="464" posY="416" />
  <Tile Type="1" posX="432" posY="432" />
  <Tile Type="85" posX="448" posY="432" />
  <Tile Type="85" posX="464" posY="432" />
  <Tile Type="32" posX="416" posY="448" />
  <Tile Type="51" posX="432" posY="448" />
  <Tile Type="85" posX="448" posY="448" />
  <Tile Type="85" posX="464" posY="448" />
  <Tile Type="1" posX="416" posY="464" />
  <Tile Type="85" posX="432" posY="464" />
  <Tile Type="85" posX="448" posY="464" />
  <Tile Type="85" posX="464" posY="464" />
  <Tile Type="1" posX="416" posY="480" />
  <Tile Type="85" posX="432" posY="480" />
  <Tile Type="85" posX="448" posY="480" />
  <Tile Type="85" posX="464" posY="480" />
  <Tile Type="2" posX="416" posY="496" />
  <Tile Type="85" posX="432" posY="496" />
  <Tile Type="85" posX="448" posY="496" />
  <Tile Type="85" posX="464" posY="496" />
  <Tile Type="1" posX="416" posY="512" />
  <Tile Type="85" posX="432" posY="512" />
  <Tile Type="85" posX="448" posY="512" />
  <Tile Type="85" posX="464" posY="512" />
  <Tile Type="2" posX="416" posY="528" />
  <Tile Type="85" posX="432" posY="528" />
  <Tile Type="85" posX="448" posY="528" />
  <Tile Type="85" posX="464" posY="528" />
  <Tile Type="1" posX="416" posY="544" />
  <Tile Type="85" posX="432" posY="544" />
  <Tile Type="85" posX="448" posY="544" />
  <Tile Type="85" posX="464" posY="544" />
  <Tile Type="2" posX="416" posY="560" />
  <Tile Type="85" posX="432" posY="560" />
  <Tile Type="85" posX="448" posY="560" />
  <Tile Type="85" posX="464" posY="560" />
  <Tile Type="1" posX="416" posY="576" />
  <Tile Type="85" posX="432" posY="576" />
  <Tile Type="85" posX="448" posY="576" />
  <Tile Type="85" posX="464" posY="576" />
  <Tile Type="2" posX="416" posY="592" />
  <Tile Type="85" posX="432" posY="592" />
  <Tile Type="85" posX="448" posY="592" />
  <Tile Type="85" posX="464" posY="592" />
  <Tile Type="1" posX="416" posY="608" />
  <Tile Type="85" posX="432" posY="608" />
  <Tile Type="85" posX="448" posY="608" />
  <Tile Type="85" posX="464" posY="608" />
  <Tile Type="2" posX="416" posY="624" />
  <Tile Type="85" posX="432" posY="624" />
  <Tile Type="85" posX="448" posY="624" />
  <Tile Type="85" posX="464" posY="624" />
	<!-- END SCREEN 1 -->

	<!-- BEGIN SCREEN 2 -->
  <Tile Type="1" posX="416" posY="640" />
  <Tile Type="85" posX="432" posY="640" />
  <Tile Type="85" posX="448" posY="640" />
  <Tile Type="85" posX="464" posY="640" />
  <Tile Type="2" posX="416" posY="656" />
  <Tile Type="85" posX="432" posY="656" />
  <Tile Type="85" posX="448" posY="656" />
  <Tile Type="85" posX="464" posY="656" />
  <Tile Type="1" posX="416" posY="672" />
  <Tile Type="85" posX="432" posY="672" />
  <Tile Type="85" posX="448" posY="672" />
  <Tile Type="85" posX="464" posY="672" />
  <Tile Type="2" posX="416" posY="688" />
  <Tile Type="85" posX="432" posY="688" />
  <Tile Type="85" posX="448" posY="688" />
  <Tile Type="85" posX="464" posY="688" />
  <Tile Type="1" posX="416" posY="704" />
  <Tile Type="66" posX="432" posY="704" />
  <Tile Type="82" posX="448" posY="704" />
  <Tile Type="1" posX="464" posY="704" />
  <Tile Type="2" posX="416" posY="720" />
  <Tile Type="67" posX="432" posY="720" />
  <Tile Type="83" posX="448" posY="720" />
  <Tile Type="2" posX="464" posY="720" />
  <Tile Type="1" posX="416" posY="736" />
  <Tile Type="66" posX="432" posY="736" />
  <Tile Type="82" posX="448" posY="736" />
  <Tile Type="1" posX="464" posY="736" />
  <Tile Type="2" posX="416" posY="752" />
  <Tile Type="67" posX="432" posY="752" />
  <Tile Type="83" posX="448" posY="752" />
  <Tile Type="2" posX="464" posY="752" />
  <Tile Type="33" posX="416" posY="768" />
  <Tile Type="46" posX="432" posY="768" />
  <Tile Type="62" posX="448" posY="768" />
  <Tile Type="50" posX="464" posY="768" />
  <Tile Type="2" posX="464" posY="784" />
  <Tile Type="1" posX="464" posY="800" />
  <Tile Type="2" posX="464" posY="816" />
  <Tile Type="1" posX="464" posY="832" />
  <Tile Type="2" posX="464" posY="848" />
  <Tile Type="1" posX="352" posY="864" />
  <Tile Type="1" posX="464" posY="864" />
  <Tile Type="2" posX="352" posY="880" />
  <Tile Type="2" posX="464" posY="880" />
  <Tile Type="1" posX="352" posY="896" />
  <Tile Type="1" posX="464" posY="896" />
  <Tile Type="2" posX="352" posY="912" />
  <Tile Type="2" posX="464" posY="912" />
  <Tile Type="1" posX="352" posY="928" />
  <Tile Type="1" posX="464" posY="928" />
  <Tile Type="2" posX="352" posY="944" />
  <Tile Type="2" posX="464" posY="944" />
  <Tile Type="1" posX="352" posY="960" />
  <Tile Type="1" posX="464" posY="960" />
  <Tile Type="2" posX="352" posY="976" />
  <Tile Type="2" posX="464" posY="976" />
  <Tile Type="1" posX="352" posY="992" />
  <Tile Type="1" posX="464" posY="992" />
  <Tile Type="2" posX="352" posY="1008" />
  <Tile Type="2" posX="464" posY="1008" />
  <Tile Type="1" posX="352" posY="1024" />
  <Tile Type="1" posX="464" posY="1024" />
  <Tile Type="2" posX="352" posY="1040" />
  <Tile Type="2" posX="464" posY="1040" />
  <Tile Type="1" posX="352" posY="1056" />
  <Tile Type="1" posX="464" posY="1056" />
  <Tile Type="2" posX="352" posY="1072" />
  <Tile Type="2" posX="464" posY="1072" />
  <Tile Type="1" posX="352" posY="1088" />
  <Tile Type="1" posX="464" posY="1088" />
  <Tile Type="2" posX="352" posY="1104" />
  <Tile Type="2" posX="464" posY="1104" />
  <Tile Type="1" posX="352" posY="1120" />
  <Tile Type="1" posX="464" posY="1120" />
  <Tile Type="2" posX="352" posY="1136" />
  <Tile Type="2" posX="464" posY="1136" />
  <Tile Type="1" posX="464" posY="1152" />
  <Tile Type="2" posX="464" posY="1168" />
  <Tile Type="1" posX="464" posY="1184" />
  <Tile Type="2" posX="464" posY="1200" />
  <Tile Type="1" posX="288" posY="1216" />
  <Tile Type="1" posX="464" posY="1216" />
  <Tile Type="2" posX="288" posY="1232" />
  <Tile Type="2" posX="464" posY="1232" />
  <Tile Type="1" posX="288" posY="1248" />
  <Tile Type="1" posX="464" posY="1248" />
  <Tile Type="2" posX="288" posY="1264" />
  <Tile Type="2" posX="464" posY="1264" />

  <Enemy posX="1024" posY="380" facingLeft="false" weapon="ASSAULT" type="SOLDIER" />
  <Enemy posX="1380" posY="200" facingLeft="true" weapon="ASSAULT" type="SOLDIER" />

  <Pickup posX="1420" posY="380" type="MAGNUM" />
	<!-- END SCREEN 2 -->

	<!-- BEGIN SCREEN 3 -->
  <Tile Type="1" posX="288" posY="1280" />
  <Tile Type="1" posX="464" posY="1280" />
  <Tile Type="2" posX="288" posY="1296" />
  <Tile Type="2" posX="464" posY="1296" />
  <Tile Type="1" posX="288" posY="1312" />
  <Tile Type="1" posX="464" posY="1312" />
  <Tile Type="2" posX="288" posY="1328" />
  <Tile Type="2" posX="464" posY="1328" />
  <Tile Type="1" posX="288" posY="1344" />
  <Tile Type="1" posX="464" posY="1344" />
  <Tile Type="2" posX="288" posY="1360" />
  <Tile Type="2" posX="464" posY="1360" />
  <Tile Type="1" posX="288" posY="1376" />
  <Tile Type="1" posX="464" posY="1376" />
  <Tile Type="2" posX="288" posY="1392" />
  <Tile Type="2" posX="464" posY="1392" />
  <Tile Type="1" posX="288" posY="1408" />
  <Tile Type="1" posX="464" posY="1408" />
  <Tile Type="2" posX="288" posY="1424" />
  <Tile Type="2" posX="464" posY="1424" />
  <Tile Type="1" posX="288" posY="1440" />
  <Tile Type="1" posX="464" posY="1440" />
  <Tile Type="2" posX="288" posY="1456" />
  <Tile Type="2" posX="464" posY="1456" />
  <Tile Type="32" posX="400" posY="1472" />
  <Tile Type="15" posX="416" posY="1472" />
  <Tile Type="31" posX="432" posY="1472" />
  <Tile Type="15" posX="448" posY="1472" />
  <Tile Type="51" posX="464" posY="1472" />
  <Tile Type="33" posX="400" posY="1488" />
  <Tile Type="14" posX="416" posY="1488" />
  <Tile Type="30" posX="432" posY="1488" />
  <Tile Type="14" posX="448" posY="1488" />
  <Tile Type="50" posX="464" posY="1488" />
  <Tile Type="1" posX="464" posY="1504" />
  <Tile Type="2" posX="464" posY="1520" />
  <Tile Type="1" posX="464" posY="1536" />
  <Tile Type="2" posX="464" posY="1552" />
  <Tile Type="1" posX="464" posY="1568" />
  <Tile Type="2" posX="464" posY="1584" />
  <Tile Type="1" posX="464" posY="1600" />
  <Tile Type="2" posX="464" posY="1616" />
  <Tile Type="1" posX="464" posY="1632" />
  <Tile Type="2" posX="464" posY="1648" />
  <Tile Type="1" posX="464" posY="1664" />
  <Tile Type="2" posX="464" posY="1680" />
  <Tile Type="1" posX="464" posY="1696" />
  <Tile Type="32" posX="432" posY="1712" />
  <Tile Type="48" posX="448" posY="1712" />
  <Tile Type="2" posX="464" posY="1712" />
  <Tile Type="33" posX="432" posY="1728" />
  <Tile Type="49" posX="448" posY="1728" />
  <Tile Type="1" posX="464" posY="1728" />
  <Tile Type="32" posX="416" posY="1744" />
  <Tile Type="15" posX="432" posY="1744" />
  <Tile Type="31" posX="448" posY="1744" />
  <Tile Type="51" posX="464" posY="1744" />
  <Tile Type="33" posX="416" posY="1760" />
  <Tile Type="14" posX="432" posY="1760" />
  <Tile Type="30" posX="448" posY="1760" />
  <Tile Type="50" posX="464" posY="1760" />
  <Tile Type="2" posX="464" posY="1776" />
  <Tile Type="1" posX="288" posY="1792" />
  <Tile Type="1" posX="464" posY="1792" />
  <Tile Type="2" posX="288" posY="1808" />
  <Tile Type="2" posX="464" posY="1808" />
  <Tile Type="1" posX="288" posY="1824" />
  <Tile Type="1" posX="464" posY="1824" />
  <Tile Type="2" posX="288" posY="1840" />
  <Tile Type="2" posX="464" posY="1840" />
  <Tile Type="1" posX="288" posY="1856" />
  <Tile Type="1" posX="464" posY="1856" />
  <Tile Type="2" posX="288" posY="1872" />
  <Tile Type="2" posX="464" posY="1872" />
  <Tile Type="1" posX="288" posY="1888" />
  <Tile Type="1" posX="464" posY="1888" />
  <Tile Type="2" posX="288" posY="1904" />
  <Tile Type="2" posX="464" posY="1904" />

  <Enemy posX="1840" posY="180" facingLeft="true" weapon="MAGNUM" type="SENTINEL" />
  <Enemy posX="1820" posY="380" facingLeft="true" weapon="ASSAULT" type="SOLDIER" />

  <Pickup posX="1850" posY="100" type="ASSAULT" />
  <Pickup posX="2050" posY="100" type="CLOAK" />
	<!-- END SCREEN 3 -->

	<!-- BEGIN SCREEN 4 -->
  <Tile Type="1" posX="288" posY="1920" />
  <Tile Type="1" posX="464" posY="1920" />
  <Tile Type="2" posX="288" posY="1936" />
  <Tile Type="2" posX="464" posY="1936" />
  <Tile Type="1" posX="288" posY="1952" />
  <Tile Type="1" posX="464" posY="1952" />
  <Tile Type="2" posX="288" posY="1968" />
  <Tile Type="2" posX="464" posY="1968" />
  <Tile Type="1" posX="288" posY="1984" />
  <Tile Type="1" posX="464" posY="1984" />
  <Tile Type="9" posX="160" posY="2000" />
  <Tile Type="25" posX="176" posY="2000" />
  <Tile Type="9" posX="192" posY="2000" />
  <Tile Type="25" posX="208" posY="2000" />
  <Tile Type="9" posX="224" posY="2000" />
  <Tile Type="25" posX="240" posY="2000" />
  <Tile Type="9" posX="256" posY="2000" />
  <Tile Type="25" posX="272" posY="2000" />
  <Tile Type="2" posX="288" posY="2000" />
  <Tile Type="2" posX="464" posY="2000" />
  <Tile Type="10" posX="160" posY="2016" />
  <Tile Type="26" posX="176" posY="2016" />
  <Tile Type="10" posX="192" posY="2016" />
  <Tile Type="26" posX="208" posY="2016" />
  <Tile Type="10" posX="224" posY="2016" />
  <Tile Type="26" posX="240" posY="2016" />
  <Tile Type="10" posX="256" posY="2016" />
  <Tile Type="26" posX="272" posY="2016" />
  <Tile Type="1" posX="288" posY="2016" />
  <Tile Type="1" posX="464" posY="2016" />
  <Tile Type="9" posX="160" posY="2032" />
  <Tile Type="25" posX="176" posY="2032" />
  <Tile Type="9" posX="192" posY="2032" />
  <Tile Type="25" posX="208" posY="2032" />
  <Tile Type="9" posX="224" posY="2032" />
  <Tile Type="25" posX="240" posY="2032" />
  <Tile Type="9" posX="256" posY="2032" />
  <Tile Type="25" posX="272" posY="2032" />
  <Tile Type="2" posX="288" posY="2032" />
  <Tile Type="2" posX="464" posY="2032" />
  <Tile Type="10" posX="160" posY="2048" />
  <Tile Type="26" posX="176" posY="2048" />
  <Tile Type="10" posX="192" posY="2048" />
  <Tile Type="26" posX="208" posY="2048" />
  <Tile Type="10" posX="224" posY="2048" />
  <Tile Type="26" posX="240" posY="2048" />
  <Tile Type="10" posX="256" posY="2048" />
  <Tile Type="26" posX="272" posY="2048" />
  <Tile Type="1" posX="288" posY="2048" />
  <Tile Type="1" posX="464" posY="2048" />
  <Tile Type="9" posX="160" posY="2064" />
  <Tile Type="25" posX="176" posY="2064" />
  <Tile Type="9" posX="192" posY="2064" />
  <Tile Type="25" posX="208" posY="2064" />
  <Tile Type="9" posX="224" posY="2064" />
  <Tile Type="25" posX="240" posY="2064" />
  <Tile Type="32" posX="256" posY="2064" />
  <Tile Type="48" posX="272" posY="2064" />
  <Tile Type="2" posX="288" posY="2064" />
  <Tile Type="2" posX="464" posY="2064" />
  <Tile Type="10" posX="160" posY="2080" />
  <Tile Type="26" posX="176" posY="2080" />
  <Tile Type="10" posX="192" posY="2080" />
  <Tile Type="26" posX="208" posY="2080" />
  <Tile Type="10" posX="224" posY="2080" />
  <Tile Type="26" posX="240" posY="2080" />
  <Tile Type="33" posX="256" posY="2080" />
  <Tile Type="49" posX="272" posY="2080" />
  <Tile Type="1" posX="288" posY="2080" />
  <Tile Type="1" posX="464" posY="2080" />
  <Tile Type="15" posX="0" posY="2096" />
  <Tile Type="31" posX="16" posY="2096" />
  <Tile Type="15" posX="32" posY="2096" />
  <Tile Type="31" posX="48" posY="2096" />
  <Tile Type="15" posX="64" posY="2096" />
  <Tile Type="31" posX="80" posY="2096" />
  <Tile Type="15" posX="96" posY="2096" />
  <Tile Type="31" posX="112" posY="2096" />
  <Tile Type="15" posX="128" posY="2096" />
  <Tile Type="31" posX="144" posY="2096" />
  <Tile Type="15" posX="160" posY="2096" />
  <Tile Type="31" posX="176" posY="2096" />
  <Tile Type="15" posX="192" posY="2096" />
  <Tile Type="31" posX="208" posY="2096" />
  <Tile Type="15" posX="224" posY="2096" />
  <Tile Type="31" posX="240" posY="2096" />
  <Tile Type="15" posX="256" posY="2096" />
  <Tile Type="31" posX="272" posY="2096" />
  <Tile Type="51" posX="288" posY="2096" />
  <Tile Type="2" posX="464" posY="2096" />
  <Tile Type="1" posX="464" posY="2112" />
  <Tile Type="32" posX="448" posY="2128" />
  <Tile Type="51" posX="464" posY="2128" />
  <Tile Type="1" posX="448" posY="2144" />
  <Tile Type="85" posX="464" posY="2144" />
  <Tile Type="32" posX="432" posY="2160" />
  <Tile Type="51" posX="448" posY="2160" />
  <Tile Type="85" posX="464" posY="2160" />
  <Tile Type="1" posX="432" posY="2176" />
  <Tile Type="85" posX="448" posY="2176" />
  <Tile Type="85" posX="464" posY="2176" />
  <Tile Type="32" posX="416" posY="2192" />
  <Tile Type="51" posX="432" posY="2192" />
  <Tile Type="85" posX="448" posY="2192" />
  <Tile Type="85" posX="464" posY="2192" />
  <Tile Type="1" posX="416" posY="2208" />
  <Tile Type="85" posX="432" posY="2208" />
  <Tile Type="85" posX="448" posY="2208" />
  <Tile Type="85" posX="464" posY="2208" />
  <Tile Type="32" posX="400" posY="2224" />
  <Tile Type="51" posX="416" posY="2224" />
  <Tile Type="85" posX="432" posY="2224" />
  <Tile Type="85" posX="448" posY="2224" />
  <Tile Type="85" posX="464" posY="2224" />
  <Tile Type="1" posX="400" posY="2240" />
  <Tile Type="85" posX="416" posY="2240" />
  <Tile Type="85" posX="432" posY="2240" />
  <Tile Type="85" posX="448" posY="2240" />
  <Tile Type="85" posX="464" posY="2240" />
  <Tile Type="32" posX="384" posY="2256" />
  <Tile Type="51" posX="400" posY="2256" />
  <Tile Type="85" posX="416" posY="2256" />
  <Tile Type="85" posX="432" posY="2256" />
  <Tile Type="85" posX="448" posY="2256" />
  <Tile Type="85" posX="464" posY="2256" />
  <Tile Type="1" posX="384" posY="2272" />
  <Tile Type="85" posX="400" posY="2272" />
  <Tile Type="85" posX="416" posY="2272" />
  <Tile Type="85" posX="432" posY="2272" />
  <Tile Type="85" posX="448" posY="2272" />
  <Tile Type="85" posX="464" posY="2272" />
  <Tile Type="32" posX="368" posY="2288" />
  <Tile Type="51" posX="384" posY="2288" />
  <Tile Type="85" posX="400" posY="2288" />
  <Tile Type="85" posX="416" posY="2288" />
  <Tile Type="85" posX="432" posY="2288" />
  <Tile Type="85" posX="448" posY="2288" />
  <Tile Type="85" posX="464" posY="2288" />
  <Tile Type="1" posX="368" posY="2304" />
  <Tile Type="85" posX="384" posY="2304" />
  <Tile Type="85" posX="400" posY="2304" />
  <Tile Type="85" posX="416" posY="2304" />
  <Tile Type="85" posX="432" posY="2304" />
  <Tile Type="85" posX="448" posY="2304" />
  <Tile Type="85" posX="464" posY="2304" />
  <Tile Type="33" posX="368" posY="2320" />
  <Tile Type="14" posX="384" posY="2320" />
  <Tile Type="30" posX="400" posY="2320" />
  <Tile Type="14" posX="416" posY="2320" />
  <Tile Type="30" posX="432" posY="2320" />
  <Tile Type="14" posX="448" posY="2320" />
  <Tile Type="50" posX="464" posY="2320" />
  <Tile Type="1" posX="464" posY="2336" />
  <Tile Type="2" posX="464" posY="2352" />
  <Tile Type="1" posX="464" posY="2368" />
  <Tile Type="2" posX="464" posY="2384" />
  <Tile Type="1" posX="288" posY="2400" />
  <Tile Type="1" posX="464" posY="2400" />
  <Tile Type="2" posX="288" posY="2416" />
  <Tile Type="2" posX="464" posY="2416" />
  <Tile Type="1" posX="288" posY="2432" />
  <Tile Type="1" posX="464" posY="2432" />
  <Tile Type="2" posX="288" posY="2448" />
  <Tile Type="2" posX="464" posY="2448" />
  <Tile Type="1" posX="288" posY="2464" />
  <Tile Type="1" posX="464" posY="2464" />
  <Tile Type="2" posX="288" posY="2480" />
  <Tile Type="2" posX="464" posY="2480" />
  <Tile Type="1" posX="288" posY="2496" />
  <Tile Type="1" posX="464" posY="2496" />
  <Tile Type="2" posX="288" posY="2512" />
  <Tile Type="2" posX="464" posY="2512" />
  <Tile Type="1" posX="288" posY="2528" />
  <Tile Type="1" posX="464" posY="2528" />
  <Tile Type="2" posX="288" posY="2544" />
  <Tile Type="2" posX="464" posY="2544" />

  <Enemy posX="2440" posY="380" facingLeft="false" weapon="MAGNUM" type="SOLDIER" />
	<!-- END SCREEN 4 -->

	<!-- BEGIN SCREEN 5 -->
  <Tile Type="1" posX="288" posY="2560" />
  <Tile Type="1" posX="464" posY="2560" />
  <Tile Type="2" posX="288" posY="2576" />
  <Tile Type="2" posX="464" posY="2576" />
  <Tile Type="1" posX="288" posY="2592" />
  <Tile Type="1" posX="464" posY="2592" />
  <Tile Type="2" posX="288" posY="2608" />
  <Tile Type="2" posX="464" posY="2608" />
  <Tile Type="1" posX="288" posY="2624" />
  <Tile Type="1" posX="464" posY="2624" />
  <Tile Type="2" posX="288" posY="2640" />
  <Tile Type="2" posX="464" posY="2640" />
  <Tile Type="1" posX="288" posY="2656" />
  <Tile Type="1" posX="464" posY="2656" />
  <Tile Type="2" posX="288" posY="2672" />
  <Tile Type="2" posX="464" posY="2672" />
  <Tile Type="1" posX="288" posY="2688" />
  <Tile Type="1" posX="464" posY="2688" />
  <Tile Type="2" posX="288" posY="2704" />
  <Tile Type="2" posX="464" posY="2704" />
  <Tile Type="1" posX="288" posY="2720" />
  <Tile Type="1" posX="464" posY="2720" />
  <Tile Type="2" posX="288" posY="2736" />
  <Tile Type="2" posX="464" posY="2736" />
  <Tile Type="1" posX="464" posY="2752" />
  <Tile Type="2" posX="464" posY="2768" />
  <Tile Type="1" posX="464" posY="2784" />
  <Tile Type="2" posX="464" posY="2800" />
  <Tile Type="1" posX="464" posY="2816" />
  <Tile Type="2" posX="464" posY="2832" />
  <Tile Type="1" posX="288" posY="2848" />
  <Tile Type="9" posX="304" posY="2848" />
  <Tile Type="25" posX="320" posY="2848" />
  <Tile Type="9" posX="336" posY="2848" />
  <Tile Type="25" posX="352" posY="2848" />
  <Tile Type="9" posX="368" posY="2848" />
  <Tile Type="25" posX="384" posY="2848" />
  <Tile Type="9" posX="400" posY="2848" />
  <Tile Type="25" posX="416" posY="2848" />
  <Tile Type="32" posX="432" posY="2848" />
  <Tile Type="15" posX="448" posY="2848" />
  <Tile Type="51" posX="464" posY="2848" />
  <Tile Type="2" posX="288" posY="2864" />
  <Tile Type="10" posX="304" posY="2864" />
  <Tile Type="26" posX="320" posY="2864" />
  <Tile Type="10" posX="336" posY="2864" />
  <Tile Type="26" posX="352" posY="2864" />
  <Tile Type="10" posX="368" posY="2864" />
  <Tile Type="26" posX="384" posY="2864" />
  <Tile Type="10" posX="400" posY="2864" />
  <Tile Type="26" posX="416" posY="2864" />
  <Tile Type="1" posX="432" posY="2864" />
  <Tile Type="54" posX="448" posY="2864" />
  <Tile Type="2" posX="464" posY="2864" />
  <Tile Type="1" posX="288" posY="2880" />
  <Tile Type="9" posX="304" posY="2880" />
  <Tile Type="25" posX="320" posY="2880" />
  <Tile Type="9" posX="336" posY="2880" />
  <Tile Type="25" posX="352" posY="2880" />
  <Tile Type="9" posX="368" posY="2880" />
  <Tile Type="25" posX="384" posY="2880" />
  <Tile Type="9" posX="400" posY="2880" />
  <Tile Type="25" posX="416" posY="2880" />
  <Tile Type="2" posX="432" posY="2880" />
  <Tile Type="54" posX="448" posY="2880" />
  <Tile Type="1" posX="464" posY="2880" />
  <Tile Type="2" posX="288" posY="2896" />
  <Tile Type="10" posX="304" posY="2896" />
  <Tile Type="26" posX="320" posY="2896" />
  <Tile Type="10" posX="336" posY="2896" />
  <Tile Type="26" posX="352" posY="2896" />
  <Tile Type="10" posX="368" posY="2896" />
  <Tile Type="26" posX="384" posY="2896" />
  <Tile Type="10" posX="400" posY="2896" />
  <Tile Type="26" posX="416" posY="2896" />
  <Tile Type="1" posX="432" posY="2896" />
  <Tile Type="54" posX="448" posY="2896" />
  <Tile Type="2" posX="464" posY="2896" />
  <Tile Type="1" posX="288" posY="2912" />
  <Tile Type="9" posX="304" posY="2912" />
  <Tile Type="25" posX="320" posY="2912" />
  <Tile Type="9" posX="336" posY="2912" />
  <Tile Type="25" posX="352" posY="2912" />
  <Tile Type="9" posX="368" posY="2912" />
  <Tile Type="25" posX="384" posY="2912" />
  <Tile Type="9" posX="400" posY="2912" />
  <Tile Type="25" posX="416" posY="2912" />
  <Tile Type="2" posX="432" posY="2912" />
  <Tile Type="54" posX="448" posY="2912" />
  <Tile Type="1" posX="464" posY="2912" />
  <Tile Type="2" posX="288" posY="2928" />
  <Tile Type="10" posX="304" posY="2928" />
  <Tile Type="26" posX="320" posY="2928" />
  <Tile Type="10" posX="336" posY="2928" />
  <Tile Type="26" posX="352" posY="2928" />
  <Tile Type="10" posX="368" posY="2928" />
  <Tile Type="26" posX="384" posY="2928" />
  <Tile Type="10" posX="400" posY="2928" />
  <Tile Type="26" posX="416" posY="2928" />
  <Tile Type="1" posX="432" posY="2928" />
  <Tile Type="54" posX="448" posY="2928" />
  <Tile Type="2" posX="464" posY="2928" />
  <Tile Type="1" posX="288" posY="2944" />
  <Tile Type="9" posX="304" posY="2944" />
  <Tile Type="25" posX="320" posY="2944" />
  <Tile Type="9" posX="336" posY="2944" />
  <Tile Type="25" posX="352" posY="2944" />
  <Tile Type="9" posX="368" posY="2944" />
  <Tile Type="25" posX="384" posY="2944" />
  <Tile Type="9" posX="400" posY="2944" />
  <Tile Type="25" posX="416" posY="2944" />
  <Tile Type="2" posX="432" posY="2944" />
  <Tile Type="54" posX="448" posY="2944" />
  <Tile Type="1" posX="464" posY="2944" />
  <Tile Type="2" posX="288" posY="2960" />
  <Tile Type="10" posX="304" posY="2960" />
  <Tile Type="26" posX="320" posY="2960" />
  <Tile Type="10" posX="336" posY="2960" />
  <Tile Type="26" posX="352" posY="2960" />
  <Tile Type="10" posX="368" posY="2960" />
  <Tile Type="26" posX="384" posY="2960" />
  <Tile Type="10" posX="400" posY="2960" />
  <Tile Type="26" posX="416" posY="2960" />
  <Tile Type="33" posX="432" posY="2960" />
  <Tile Type="14" posX="448" posY="2960" />
  <Tile Type="50" posX="464" posY="2960" />
  <Tile Type="1" posX="464" posY="2976" />
  <Tile Type="2" posX="464" posY="2992" />
  <Tile Type="32" posX="352" posY="3008" />
  <Tile Type="48" posX="368" posY="3008" />
  <Tile Type="1" posX="464" posY="3008" />
  <Tile Type="33" posX="352" posY="3024" />
  <Tile Type="49" posX="368" posY="3024" />
  <Tile Type="2" posX="464" posY="3024" />
  <Tile Type="1" posX="464" posY="3040" />
  <Tile Type="2" posX="464" posY="3056" />
  <Tile Type="1" posX="288" posY="3072" />
  <Tile Type="1" posX="464" posY="3072" />
  <Tile Type="2" posX="288" posY="3088" />
  <Tile Type="2" posX="464" posY="3088" />
  <Tile Type="1" posX="288" posY="3104" />
  <Tile Type="1" posX="464" posY="3104" />
  <Tile Type="2" posX="288" posY="3120" />
  <Tile Type="2" posX="464" posY="3120" />
  <Tile Type="1" posX="288" posY="3136" />
  <Tile Type="1" posX="464" posY="3136" />
  <Tile Type="2" posX="288" posY="3152" />
  <Tile Type="2" posX="464" posY="3152" />
  <Tile Type="1" posX="288" posY="3168" />
  <Tile Type="1" posX="464" posY="3168" />
  <Tile Type="2" posX="288" posY="3184" />
  <Tile Type="2" posX="464" posY="3184" />

  <Enemy posX="2900" posY="100" facingLeft="false" weapon="ASSAULT" type="SENTINEL" />
  <Enemy posX="3150" posY="380" facingLeft="true" weapon="ASSAULT" type="SOLDIER" />

  <Pickup posX="2900" posY="380" type="HEALTH" />
	<!-- END SCREEN 5 -->

	<!-- BEGIN SCREEN 6 -->
  <Tile Type="1" posX="288" posY="3200" />
  <Tile Type="1" posX="464" posY="3200" />
  <Tile Type="2" posX="288" posY="3216" />
  <Tile Type="2" posX="464" posY="3216" />
  <Tile Type="1" posX="288" posY="3232" />
  <Tile Type="1" posX="464" posY="3232" />
  <Tile Type="2" posX="288" posY="3248" />
  <Tile Type="2" posX="464" posY="3248" />
  <Tile Type="1" posX="288" posY="3264" />
  <Tile Type="1" posX="464" posY="3264" />
  <Tile Type="2" posX="288" posY="3280" />
  <Tile Type="2" posX="464" posY="3280" />
  <Tile Type="1" posX="288" posY="3296" />
  <Tile Type="1" posX="464" posY="3296" />
  <Tile Type="2" posX="288" posY="3312" />
  <Tile Type="2" posX="464" posY="3312" />
  <Tile Type="1" posX="288" posY="3328" />
  <Tile Type="1" posX="464" posY="3328" />
  <Tile Type="2" posX="288" posY="3344" />
  <Tile Type="2" posX="464" posY="3344" />
  <Tile Type="1" posX="288" posY="3360" />
  <Tile Type="1" posX="464" posY="3360" />
  <Tile Type="2" posX="288" posY="3376" />
  <Tile Type="2" posX="464" posY="3376" />
  <Tile Type="1" posX="464" posY="3392" />
  <Tile Type="2" posX="464" posY="3408" />
  <Tile Type="1" posX="464" posY="3424" />
  <Tile Type="2" posX="464" posY="3440" />
  <Tile Type="9" posX="160" posY="3456" />
  <Tile Type="25" posX="176" posY="3456" />
  <Tile Type="1" posX="192" posY="3456" />
  <Tile Type="1" posX="464" posY="3456" />
  <Tile Type="10" posX="160" posY="3472" />
  <Tile Type="26" posX="176" posY="3472" />
  <Tile Type="2" posX="192" posY="3472" />
  <Tile Type="2" posX="464" posY="3472" />
  <Tile Type="9" posX="160" posY="3488" />
  <Tile Type="25" posX="176" posY="3488" />
  <Tile Type="1" posX="192" posY="3488" />
  <Tile Type="1" posX="464" posY="3488" />
  <Tile Type="10" posX="160" posY="3504" />
  <Tile Type="26" posX="176" posY="3504" />
  <Tile Type="2" posX="192" posY="3504" />
  <Tile Type="2" posX="464" posY="3504" />
  <Tile Type="9" posX="160" posY="3520" />
  <Tile Type="25" posX="176" posY="3520" />
  <Tile Type="1" posX="192" posY="3520" />
  <Tile Type="1" posX="464" posY="3520" />
  <Tile Type="10" posX="160" posY="3536" />
  <Tile Type="26" posX="176" posY="3536" />
  <Tile Type="2" posX="192" posY="3536" />
  <Tile Type="2" posX="464" posY="3536" />
  <Tile Type="9" posX="160" posY="3552" />
  <Tile Type="25" posX="176" posY="3552" />
  <Tile Type="1" posX="192" posY="3552" />
  <Tile Type="1" posX="464" posY="3552" />
  <Tile Type="10" posX="160" posY="3568" />
  <Tile Type="26" posX="176" posY="3568" />
  <Tile Type="2" posX="192" posY="3568" />
  <Tile Type="2" posX="464" posY="3568" />
  <Tile Type="9" posX="160" posY="3584" />
  <Tile Type="25" posX="176" posY="3584" />
  <Tile Type="1" posX="192" posY="3584" />
  <Tile Type="32" posX="416" posY="3584" />
  <Tile Type="15" posX="432" posY="3584" />
  <Tile Type="31" posX="448" posY="3584" />
  <Tile Type="51" posX="464" posY="3584" />
  <Tile Type="10" posX="160" posY="3600" />
  <Tile Type="26" posX="176" posY="3600" />
  <Tile Type="2" posX="192" posY="3600" />
  <Tile Type="33" posX="416" posY="3600" />
  <Tile Type="14" posX="432" posY="3600" />
  <Tile Type="30" posX="448" posY="3600" />
  <Tile Type="50" posX="464" posY="3600" />
  <Tile Type="9" posX="160" posY="3616" />
  <Tile Type="25" posX="176" posY="3616" />
  <Tile Type="1" posX="192" posY="3616" />
  <Tile Type="1" posX="464" posY="3616" />
  <Tile Type="10" posX="160" posY="3632" />
  <Tile Type="26" posX="176" posY="3632" />
  <Tile Type="2" posX="192" posY="3632" />
  <Tile Type="2" posX="464" posY="3632" />
  <Tile Type="1" posX="464" posY="3648" />
  <Tile Type="2" posX="464" posY="3664" />
  <Tile Type="1" posX="464" posY="3680" />
  <Tile Type="2" posX="464" posY="3696" />
  <Tile Type="1" posX="464" posY="3712" />
  <Tile Type="2" posX="464" posY="3728" />
  <Tile Type="1" posX="464" posY="3744" />
  <Tile Type="2" posX="464" posY="3760" />
  <Tile Type="1" posX="464" posY="3776" />
  <Tile Type="2" posX="464" posY="3792" />
  <Tile Type="1" posX="464" posY="3808" />
  <Tile Type="2" posX="464" posY="3824" />

  <Enemy posX="3560" posY="380" facingLeft="false" weapon="ASSAULT" type="SOLDIER" />
  <Enemy posX="3540" posY="380" facingLeft="true" weapon="MAGNUM" type="SENTINEL" />

  <Pickup posX="3540" posY="100" type="HEALTH" />
  <Pickup posX="3580" posY="100" type="ASSAULT" />
  <Pickup posX="3620" posY="100" type="MAGNUM" />
	<!-- END SCREEN 6 -->

	<!-- BEGIN SCREEN 7 -->
  <Tile Type="1" posX="464" posY="3840" />
  <Tile Type="2" posX="464" posY="3856" />
  <Tile Type="1" posX="464" posY="3872" />
  <Tile Type="2" posX="464" posY="3888" />
  <Tile Type="1" posX="464" posY="3904" />
  <Tile Type="2" posX="464" posY="3920" />
  <Tile Type="1" posX="464" posY="3936" />
  <Tile Type="2" posX="464" posY="3952" />
  <Tile Type="1" posX="464" posY="3968" />
  <Tile Type="2" posX="464" posY="3984" />
  <Tile Type="1" posX="464" posY="4000" />
  <Tile Type="2" posX="464" posY="4016" />
  <Tile Type="1" posX="464" posY="4032" />
  <Tile Type="2" posX="464" posY="4048" />
  <Tile Type="1" posX="464" posY="4064" />
  <Tile Type="2" posX="464" posY="4080" />
  <Tile Type="1" posX="464" posY="4096" />
  <Tile Type="2" posX="464" posY="4112" />
  <Tile Type="1" posX="464" posY="4128" />
  <Tile Type="2" posX="464" posY="4144" />
  <Tile Type="1" posX="464" posY="4160" />
  <Tile Type="2" posX="464" posY="4176" />
  <Tile Type="1" posX="464" posY="4192" />
  <Tile Type="2" posX="464" posY="4208" />
  <Tile Type="1" posX="464" posY="4224" />
  <Tile Type="2" posX="464" posY="4240" />
  <Tile Type="1" posX="464" posY="4256" />
  <Tile Type="2" posX="464" posY="4272" />
  <Tile Type="1" posX="464" posY="4288" />
  <Tile Type="2" posX="464" posY="4304" />
  <Tile Type="1" posX="464" posY="4320" />
  <Tile Type="2" posX="464" posY="4336" />
  <Tile Type="1" posX="464" posY="4352" />
  <Tile Type="2" posX="464" posY="4368" />
  <Tile Type="1" posX="464" posY="4384" />
  <Tile Type="2" posX="464" posY="4400" />
  <Tile Type="1" posX="464" posY="4416" />
  <Tile Type="2" posX="464" posY="4432" />
  <Tile Type="1" posX="464" posY="4448" />

  <Enemy posX="4160" posY="380" facingLeft="true" weapon="ASSAULT" type="SENTINEL" />
  <Enemy posX="4260" posY="380" facingLeft="true" weapon="MAGNUM" type="SENTINEL" />
  <Enemy posX="4360" posY="380" facingLeft="true" weapon="MAGNUM" type="SENTINEL" />
	<!-- END SCREEN 7 -->

	<!-- BEGIN SCREEN 8 -->

	<!-- END SCREEN 8 -->
</Map>